{"info": {"split": "train_full", "version": "1.0", "license": "Creative Commons Attribution (CC-BY 4.0)", "date": "05/05/2023"}, "questions": [{"split": "train_full", "image_filename": "CLEVR_train_full_000000.png", "image_index": 0, "image": "CLEVR_train_full_000000", "question": "big purple rubber cube", "program": [{"type": "scene", "inputs": [], "_output": [0], "value_inputs": []}, {"type": "filter_size", "inputs": [0], "_output": [], "value_inputs": ["large"]}, {"type": "filter_color", "inputs": [1], "_output": [], "value_inputs": ["purple"]}, {"type": "filter_material", "inputs": [2], "_output": [], "value_inputs": ["rubber"]}, {"type": "filter_shape", "inputs": [3], "_output": [], "value_inputs": ["cube"]}, {"type": "count", "inputs": [4], "_output": 0, "value_inputs": []}], "answer": 0, "template_filename": "1obj.json", "question_family_index": 0, "question_index": 0}, {"split": "train_full", "image_filename": "CLEVR_train_full_000000.png", "image_index": 0, "image": "CLEVR_train_full_000000", "question": "small gray rubber ball", "program": [{"type": "scene", "inputs": [], "_output": [0], "value_inputs": []}, {"type": "filter_size", "inputs": [0], "_output": [0], "value_inputs": ["small"]}, {"type": "filter_color", "inputs": [1], "_output": [0], "value_inputs": ["gray"]}, {"type": "filter_material", "inputs": [2], "_output": [0], "value_inputs": ["rubber"]}, {"type": "filter_shape", "inputs": [3], "_output": [0], "value_inputs": ["sphere"]}, {"type": "count", "inputs": [4], "_output": 1, "value_inputs": []}], "answer": 1, "template_filename": "1obj.json", "question_family_index": 0, "question_index": 1}, {"split": "train_full", "image_filename": "CLEVR_train_full_000000.png", "image_index": 0, "image": "CLEVR_train_full_000000", "question": "tiny gray matte cylinder", "program": [{"type": "scene", "inputs": [], "_output": [0], "value_inputs": []}, {"type": "filter_size", "inputs": [0], "_output": [0], "value_inputs": ["small"]}, {"type": "filter_color", "inputs": [1], "_output": [0], "value_inputs": ["gray"]}, {"type": "filter_material", "inputs": [2], "_output": [0], "value_inputs": ["rubber"]}, {"type": "filter_shape", "inputs": [3], "_output": [], "value_inputs": ["cylinder"]}, {"type": "count", "inputs": [4], "_output": 0, "value_inputs": []}], "answer": 0, "template_filename": "1obj.json", "question_family_index": 0, "question_index": 2}, {"split": "train_full", "image_filename": "CLEVR_train_full_000001.png", "image_index": 1, "image": "CLEVR_train_full_000001", "question": "big gray metal cube", "program": [{"type": "scene", "inputs": [], "_output": [0], "value_inputs": []}, {"type": "filter_size", "inputs": [0], "_output": [0], "value_inputs": ["large"]}, {"type": "filter_color", "inputs": [1], "_output": [0], "value_inputs": ["gray"]}, {"type": "filter_material", "inputs": [2], "_output": [0], "value_inputs": ["metal"]}, {"type": "filter_shape", "inputs": [3], "_output": [0], "value_inputs": ["cube"]}, {"type": "count", "inputs": [4], "_output": 1, "value_inputs": []}], "answer": 1, "template_filename": "1obj.json", "question_family_index": 0, "question_index": 3}, {"split": "train_full", "image_filename": "CLEVR_train_full_000001.png", "image_index": 1, "image": "CLEVR_train_full_000001", "question": "large brown metallic cylinder", "program": [{"type": "scene", "inputs": [], "_output": [0], "value_inputs": []}, {"type": "filter_size", "inputs": [0], "_output": [0], "value_inputs": ["large"]}, {"type": "filter_color", "inputs": [1], "_output": [], "value_inputs": ["brown"]}, {"type": "filter_material", "inputs": [2], "_output": [], "value_inputs": ["metal"]}, {"type": "filter_shape", "inputs": [3], "_output": [], "value_inputs": ["cylinder"]}, {"type": "count", "inputs": [4], "_output": 0, "value_inputs": []}], "answer": 0, "template_filename": "1obj.json", "question_family_index": 0, "question_index": 4}, {"split": "train_full", "image_filename": "CLEVR_train_full_000002.png", "image_index": 2, "image": "CLEVR_train_full_000002", "question": "tiny purple rubber cylinder", "program": [{"type": "scene", "inputs": [], "_output": [0], "value_inputs": []}, {"type": "filter_size", "inputs": [0], "_output": [0], "value_inputs": ["small"]}, {"type": "filter_color", "inputs": [1], "_output": [0], "value_inputs": ["purple"]}, {"type": "filter_material", "inputs": [2], "_output": [0], "value_inputs": ["rubber"]}, {"type": "filter_shape", "inputs": [3], "_output": [0], "value_inputs": ["cylinder"]}, {"type": "count", "inputs": [4], "_output": 1, "value_inputs": []}], "answer": 1, "template_filename": "1obj.json", "question_family_index": 0, "question_index": 5}, {"split": "train_full", "image_filename": "CLEVR_train_full_000002.png", "image_index": 2, "image": "CLEVR_train_full_000002", "question": "large gray metallic block", "program": [{"type": "scene", "inputs": [], "_output": [0], "value_inputs": []}, {"type": "filter_size", "inputs": [0], "_output": [], "value_inputs": ["large"]}, {"type": "filter_color", "inputs": [1], "_output": [], "value_inputs": ["gray"]}, {"type": "filter_material", "inputs": [2], "_output": [], "value_inputs": ["metal"]}, {"type": "filter_shape", "inputs": [3], "_output": [], "value_inputs": ["cube"]}, {"type": "count", "inputs": [4], "_output": 0, "value_inputs": []}], "answer": 0, "template_filename": "1obj.json", "question_family_index": 0, "question_index": 6}, {"split": "train_full", "image_filename": "CLEVR_train_full_000003.png", "image_index": 3, "image": "CLEVR_train_full_000003", "question": "big yellow rubber cube", "program": [{"type": "scene", "inputs": [], "_output": [0], "value_inputs": []}, {"type": "filter_size", "inputs": [0], "_output": [0], "value_inputs": ["large"]}, {"type": "filter_color", "inputs": [1], "_output": [0], "value_inputs": ["yellow"]}, {"type": "filter_material", "inputs": [2], "_output": [0], "value_inputs": ["rubber"]}, {"type": "filter_shape", "inputs": [3], "_output": [0], "value_inputs": ["cube"]}, {"type": "count", "inputs": [4], "_output": 1, "value_inputs": []}], "answer": 1, "template_filename": "1obj.json", "question_family_index": 0, "question_index": 7}, {"split": "train_full", "image_filename": "CLEVR_train_full_000003.png", "image_index": 3, "image": "CLEVR_train_full_000003", "question": "small cyan shiny block", "program": [{"type": "scene", "inputs": [], "_output": [0], "value_inputs": []}, {"type": "filter_size", "inputs": [0], "_output": [], "value_inputs": ["small"]}, {"type": "filter_color", "inputs": [1], "_output": [], "value_inputs": ["cyan"]}, {"type": "filter_material", "inputs": [2], "_output": [], "value_inputs": ["metal"]}, {"type": "filter_shape", "inputs": [3], "_output": [], "value_inputs": ["cube"]}, {"type": "count", "inputs": [4], "_output": 0, "value_inputs": []}], "answer": 0, "template_filename": "1obj.json", "question_family_index": 0, "question_index": 8}, {"split": "train_full", "image_filename": "CLEVR_train_full_000004.png", "image_index": 4, "image": "CLEVR_train_full_000004", "question": "tiny green metal cylinder", "program": [{"type": "scene", "inputs": [], "_output": [0], "value_inputs": []}, {"type": "filter_size", "inputs": [0], "_output": [0], "value_inputs": ["small"]}, {"type": "filter_color", "inputs": [1], "_output": [0], "value_inputs": ["green"]}, {"type": "filter_material", "inputs": [2], "_output": [0], "value_inputs": ["metal"]}, {"type": "filter_shape", "inputs": [3], "_output": [0], "value_inputs": ["cylinder"]}, {"type": "count", "inputs": [4], "_output": 1, "value_inputs": []}], "answer": 1, "template_filename": "1obj.json", "question_family_index": 0, "question_index": 9}, {"split": "train_full", "image_filename": "CLEVR_train_full_000004.png", "image_index": 4, "image": "CLEVR_train_full_000004", "question": "big brown rubber block", "program": [{"type": "scene", "inputs": [], "_output": [0], "value_inputs": []}, {"type": "filter_size", "inputs": [0], "_output": [], "value_inputs": ["large"]}, {"type": "filter_color", "inputs": [1], "_output": [], "value_inputs": ["brown"]}, {"type": "filter_material", "inputs": [2], "_output": [], "value_inputs": ["rubber"]}, {"type": "filter_shape", "inputs": [3], "_output": [], "value_inputs": ["cube"]}, {"type": "count", "inputs": [4], "_output": 0, "value_inputs": []}], "answer": 0, "template_filename": "1obj.json", "question_family_index": 0, "question_index": 10}, {"split": "train_full", "image_filename": "CLEVR_train_full_000005.png", "image_index": 5, "image": "CLEVR_train_full_000005", "question": "small red rubber cube", "program": [{"type": "scene", "inputs": [], "_output": [0], "value_inputs": []}, {"type": "filter_size", "inputs": [0], "_output": [0], "value_inputs": ["small"]}, {"type": "filter_color", "inputs": [1], "_output": [0], "value_inputs": ["red"]}, {"type": "filter_material", "inputs": [2], "_output": [0], "value_inputs": ["rubber"]}, {"type": "filter_shape", "inputs": [3], "_output": [0], "value_inputs": ["cube"]}, {"type": "count", "inputs": [4], "_output": 1, "value_inputs": []}], "answer": 1, "template_filename": "1obj.json", "question_family_index": 0, "question_index": 11}, {"split": "train_full", "image_filename": "CLEVR_train_full_000005.png", "image_index": 5, "image": "CLEVR_train_full_000005", "question": "tiny blue rubber block", "program": [{"type": "scene", "inputs": [], "_output": [0], "value_inputs": []}, {"type": "filter_size", "inputs": [0], "_output": [0], "value_inputs": ["small"]}, {"type": "filter_color", "inputs": [1], "_output": [], "value_inputs": ["blue"]}, {"type": "filter_material", "inputs": [2], "_output": [], "value_inputs": ["rubber"]}, {"type": "filter_shape", "inputs": [3], "_output": [], "value_inputs": ["cube"]}, {"type": "count", "inputs": [4], "_output": 0, "value_inputs": []}], "answer": 0, "template_filename": "1obj.json", "question_family_index": 0, "question_index": 12}, {"split": "train_full", "image_filename": "CLEVR_train_full_000006.png", "image_index": 6, "image": "CLEVR_train_full_000006", "question": "big blue metal cylinder", "program": [{"type": "scene", "inputs": [], "_output": [0], "value_inputs": []}, {"type": "filter_size", "inputs": [0], "_output": [0], "value_inputs": ["large"]}, {"type": "filter_color", "inputs": [1], "_output": [0], "value_inputs": ["blue"]}, {"type": "filter_material", "inputs": [2], "_output": [0], "value_inputs": ["metal"]}, {"type": "filter_shape", "inputs": [3], "_output": [0], "value_inputs": ["cylinder"]}, {"type": "count", "inputs": [4], "_output": 1, "value_inputs": []}], "answer": 1, "template_filename": "1obj.json", "question_family_index": 0, "question_index": 13}, {"split": "train_full", "image_filename": "CLEVR_train_full_000007.png", "image_index": 7, "image": "CLEVR_train_full_000007", "question": "tiny gray metallic ball", "program": [{"type": "scene", "inputs": [], "_output": [0], "value_inputs": []}, {"type": "filter_size", "inputs": [0], "_output": [], "value_inputs": ["small"]}, {"type": "filter_color", "inputs": [1], "_output": [], "value_inputs": ["gray"]}, {"type": "filter_material", "inputs": [2], "_output": [], "value_inputs": ["metal"]}, {"type": "filter_shape", "inputs": [3], "_output": [], "value_inputs": ["sphere"]}, {"type": "count", "inputs": [4], "_output": 0, "value_inputs": []}], "answer": 0, "template_filename": "1obj.json", "question_family_index": 0, "question_index": 14}, {"split": "train_full", "image_filename": "CLEVR_train_full_000007.png", "image_index": 7, "image": "CLEVR_train_full_000007", "question": "big gray rubber cube", "program": [{"type": "scene", "inputs": [], "_output": [0], "value_inputs": []}, {"type": "filter_size", "inputs": [0], "_output": [0], "value_inputs": ["large"]}, {"type": "filter_color", "inputs": [1], "_output": [0], "value_inputs": ["gray"]}, {"type": "filter_material", "inputs": [2], "_output": [0], "value_inputs": ["rubber"]}, {"type": "filter_shape", "inputs": [3], "_output": [0], "value_inputs": ["cube"]}, {"type": "count", "inputs": [4], "_output": 1, "value_inputs": []}], "answer": 1, "template_filename": "1obj.json", "question_family_index": 0, "question_index": 15}, {"split": "train_full", "image_filename": "CLEVR_train_full_000008.png", "image_index": 8, "image": "CLEVR_train_full_000008", "question": "big blue shiny cylinder", "program": [{"type": "scene", "inputs": [], "_output": [0], "value_inputs": []}, {"type": "filter_size", "inputs": [0], "_output": [], "value_inputs": ["large"]}, {"type": "filter_color", "inputs": [1], "_output": [], "value_inputs": ["blue"]}, {"type": "filter_material", "inputs": [2], "_output": [], "value_inputs": ["metal"]}, {"type": "filter_shape", "inputs": [3], "_output": [], "value_inputs": ["cylinder"]}, {"type": "count", "inputs": [4], "_output": 0, "value_inputs": []}], "answer": 0, "template_filename": "1obj.json", "question_family_index": 0, "question_index": 16}, {"split": "train_full", "image_filename": "CLEVR_train_full_000008.png", "image_index": 8, "image": "CLEVR_train_full_000008", "question": "small blue shiny cube", "program": [{"type": "scene", "inputs": [], "_output": [0], "value_inputs": []}, {"type": "filter_size", "inputs": [0], "_output": [0], "value_inputs": ["small"]}, {"type": "filter_color", "inputs": [1], "_output": [0], "value_inputs": ["blue"]}, {"type": "filter_material", "inputs": [2], "_output": [0], "value_inputs": ["metal"]}, {"type": "filter_shape", "inputs": [3], "_output": [0], "value_inputs": ["cube"]}, {"type": "count", "inputs": [4], "_output": 1, "value_inputs": []}], "answer": 1, "template_filename": "1obj.json", "question_family_index": 0, "question_index": 17}, {"split": "train_full", "image_filename": "CLEVR_train_full_000008.png", "image_index": 8, "image": "CLEVR_train_full_000008", "question": "large green rubber block", "program": [{"type": "scene", "inputs": [], "_output": [0], "value_inputs": []}, {"type": "filter_size", "inputs": [0], "_output": [], "value_inputs": ["large"]}, {"type": "filter_color", "inputs": [1], "_output": [], "value_inputs": ["green"]}, {"type": "filter_material", "inputs": [2], "_output": [], "value_inputs": ["rubber"]}, {"type": "filter_shape", "inputs": [3], "_output": [], "value_inputs": ["cube"]}, {"type": "count", "inputs": [4], "_output": 0, "value_inputs": []}], "answer": 0, "template_filename": "1obj.json", "question_family_index": 0, "question_index": 18}, {"split": "train_full", "image_filename": "CLEVR_train_full_000009.png", "image_index": 9, "image": "CLEVR_train_full_000009", "question": "big yellow rubber sphere", "program": [{"type": "scene", "inputs": [], "_output": [0], "value_inputs": []}, {"type": "filter_size", "inputs": [0], "_output": [0], "value_inputs": ["large"]}, {"type": "filter_color", "inputs": [1], "_output": [0], "value_inputs": ["yellow"]}, {"type": "filter_material", "inputs": [2], "_output": [0], "value_inputs": ["rubber"]}, {"type": "filter_shape", "inputs": [3], "_output": [0], "value_inputs": ["sphere"]}, {"type": "count", "inputs": [4], "_output": 1, "value_inputs": []}], "answer": 1, "template_filename": "1obj.json", "question_family_index": 0, "question_index": 19}, {"split": "train_full", "image_filename": "CLEVR_train_full_000009.png", "image_index": 9, "image": "CLEVR_train_full_000009", "question": "big purple metal cylinder", "program": [{"type": "scene", "inputs": [], "_output": [0], "value_inputs": []}, {"type": "filter_size", "inputs": [0], "_output": [0], "value_inputs": ["large"]}, {"type": "filter_color", "inputs": [1], "_output": [], "value_inputs": ["purple"]}, {"type": "filter_material", "inputs": [2], "_output": [], "value_inputs": ["metal"]}, {"type": "filter_shape", "inputs": [3], "_output": [], "value_inputs": ["cylinder"]}, {"type": "count", "inputs": [4], "_output": 0, "value_inputs": []}], "answer": 0, "template_filename": "1obj.json", "question_family_index": 0, "question_index": 20}, {"split": "train_full", "image_filename": "CLEVR_train_full_000010.png", "image_index": 10, "image": "CLEVR_train_full_000010", "question": "tiny red shiny sphere", "program": [{"type": "scene", "inputs": [], "_output": [0], "value_inputs": []}, {"type": "filter_size", "inputs": [0], "_output": [0], "value_inputs": ["small"]}, {"type": "filter_color", "inputs": [1], "_output": [], "value_inputs": ["red"]}, {"type": "filter_material", "inputs": [2], "_output": [], "value_inputs": ["metal"]}, {"type": "filter_shape", "inputs": [3], "_output": [], "value_inputs": ["sphere"]}, {"type": "count", "inputs": [4], "_output": 0, "value_inputs": []}], "answer": 0, "template_filename": "1obj.json", "question_family_index": 0, "question_index": 21}, {"split": "train_full", "image_filename": "CLEVR_train_full_000010.png", "image_index": 10, "image": "CLEVR_train_full_000010", "question": "tiny brown metallic ball", "program": [{"type": "scene", "inputs": [], "_output": [0], "value_inputs": []}, {"type": "filter_size", "inputs": [0], "_output": [0], "value_inputs": ["small"]}, {"type": "filter_color", "inputs": [1], "_output": [0], "value_inputs": ["brown"]}, {"type": "filter_material", "inputs": [2], "_output": [0], "value_inputs": ["metal"]}, {"type": "filter_shape", "inputs": [3], "_output": [0], "value_inputs": ["sphere"]}, {"type": "count", "inputs": [4], "_output": 1, "value_inputs": []}], "answer": 1, "template_filename": "1obj.json", "question_family_index": 0, "question_index": 22}, {"split": "train_full", "image_filename": "CLEVR_train_full_000010.png", "image_index": 10, "image": "CLEVR_train_full_000010", "question": "large blue rubber ball", "program": [{"type": "scene", "inputs": [], "_output": [0], "value_inputs": []}, {"type": "filter_size", "inputs": [0], "_output": [], "value_inputs": ["large"]}, {"type": "filter_color", "inputs": [1], "_output": [], "value_inputs": ["blue"]}, {"type": "filter_material", "inputs": [2], "_output": [], "value_inputs": ["rubber"]}, {"type": "filter_shape", "inputs": [3], "_output": [], "value_inputs": ["sphere"]}, {"type": "count", "inputs": [4], "_output": 0, "value_inputs": []}], "answer": 0, "template_filename": "1obj.json", "question_family_index": 0, "question_index": 23}, {"split": "train_full", "image_filename": "CLEVR_train_full_000011.png", "image_index": 11, "image": "CLEVR_train_full_000011", "question": "small gray matte block", "program": [{"type": "scene", "inputs": [], "_output": [0], "value_inputs": []}, {"type": "filter_size", "inputs": [0], "_output": [0], "value_inputs": ["small"]}, {"type": "filter_color", "inputs": [1], "_output": [0], "value_inputs": ["gray"]}, {"type": "filter_material", "inputs": [2], "_output": [0], "value_inputs": ["rubber"]}, {"type": "filter_shape", "inputs": [3], "_output": [0], "value_inputs": ["cube"]}, {"type": "count", "inputs": [4], "_output": 1, "value_inputs": []}], "answer": 1, "template_filename": "1obj.json", "question_family_index": 0, "question_index": 24}, {"split": "train_full", "image_filename": "CLEVR_train_full_000011.png", "image_index": 11, "image": "CLEVR_train_full_000011", "question": "big blue rubber block", "program": [{"type": "scene", "inputs": [], "_output": [0], "value_inputs": []}, {"type": "filter_size", "inputs": [0], "_output": [], "value_inputs": ["large"]}, {"type": "filter_color", "inputs": [1], "_output": [], "value_inputs": ["blue"]}, {"type": "filter_material", "inputs": [2], "_output": [], "value_inputs": ["rubber"]}, {"type": "filter_shape", "inputs": [3], "_output": [], "value_inputs": ["cube"]}, {"type": "count", "inputs": [4], "_output": 0, "value_inputs": []}], "answer": 0, "template_filename": "1obj.json", "question_family_index": 0, "question_index": 25}, {"split": "train_full", "image_filename": "CLEVR_train_full_000012.png", "image_index": 12, "image": "CLEVR_train_full_000012", "question": "tiny yellow metallic sphere", "program": [{"type": "scene", "inputs": [], "_output": [0], "value_inputs": []}, {"type": "filter_size", "inputs": [0], "_output": [0], "value_inputs": ["small"]}, {"type": "filter_color", "inputs": [1], "_output": [0], "value_inputs": ["yellow"]}, {"type": "filter_material", "inputs": [2], "_output": [0], "value_inputs": ["metal"]}, {"type": "filter_shape", "inputs": [3], "_output": [0], "value_inputs": ["sphere"]}, {"type": "count", "inputs": [4], "_output": 1, "value_inputs": []}], "answer": 1, "template_filename": "1obj.json", "question_family_index": 0, "question_index": 26}, {"split": "train_full", "image_filename": "CLEVR_train_full_000013.png", "image_index": 13, "image": "CLEVR_train_full_000013", "question": "large brown metal cylinder", "program": [{"type": "scene", "inputs": [], "_output": [0], "value_inputs": []}, {"type": "filter_size", "inputs": [0], "_output": [0], "value_inputs": ["large"]}, {"type": "filter_color", "inputs": [1], "_output": [], "value_inputs": ["brown"]}, {"type": "filter_material", "inputs": [2], "_output": [], "value_inputs": ["metal"]}, {"type": "filter_shape", "inputs": [3], "_output": [], "value_inputs": ["cylinder"]}, {"type": "count", "inputs": [4], "_output": 0, "value_inputs": []}], "answer": 0, "template_filename": "1obj.json", "question_family_index": 0, "question_index": 27}, {"split": "train_full", "image_filename": "CLEVR_train_full_000013.png", "image_index": 13, "image": "CLEVR_train_full_000013", "question": "large red matte sphere", "program": [{"type": "scene", "inputs": [], "_output": [0], "value_inputs": []}, {"type": "filter_size", "inputs": [0], "_output": [0], "value_inputs": ["large"]}, {"type": "filter_color", "inputs": [1], "_output": [0], "value_inputs": ["red"]}, {"type": "filter_material", "inputs": [2], "_output": [0], "value_inputs": ["rubber"]}, {"type": "filter_shape", "inputs": [3], "_output": [0], "value_inputs": ["sphere"]}, {"type": "count", "inputs": [4], "_output": 1, "value_inputs": []}], "answer": 1, "template_filename": "1obj.json", "question_family_index": 0, "question_index": 28}, {"split": "train_full", "image_filename": "CLEVR_train_full_000013.png", "image_index": 13, "image": "CLEVR_train_full_000013", "question": "small green shiny block", "program": [{"type": "scene", "inputs": [], "_output": [0], "value_inputs": []}, {"type": "filter_size", "inputs": [0], "_output": [], "value_inputs": ["small"]}, {"type": "filter_color", "inputs": [1], "_output": [], "value_inputs": ["green"]}, {"type": "filter_material", "inputs": [2], "_output": [], "value_inputs": ["metal"]}, {"type": "filter_shape", "inputs": [3], "_output": [], "value_inputs": ["cube"]}, {"type": "count", "inputs": [4], "_output": 0, "value_inputs": []}], "answer": 0, "template_filename": "1obj.json", "question_family_index": 0, "question_index": 29}, {"split": "train_full", "image_filename": "CLEVR_train_full_000014.png", "image_index": 14, "image": "CLEVR_train_full_000014", "question": "large blue matte sphere", "program": [{"type": "scene", "inputs": [], "_output": [0], "value_inputs": []}, {"type": "filter_size", "inputs": [0], "_output": [0], "value_inputs": ["large"]}, {"type": "filter_color", "inputs": [1], "_output": [0], "value_inputs": ["blue"]}, {"type": "filter_material", "inputs": [2], "_output": [0], "value_inputs": ["rubber"]}, {"type": "filter_shape", "inputs": [3], "_output": [0], "value_inputs": ["sphere"]}, {"type": "count", "inputs": [4], "_output": 1, "value_inputs": []}], "answer": 1, "template_filename": "1obj.json", "question_family_index": 0, "question_index": 30}, {"split": "train_full", "image_filename": "CLEVR_train_full_000014.png", "image_index": 14, "image": "CLEVR_train_full_000014", "question": "tiny yellow rubber cube", "program": [{"type": "scene", "inputs": [], "_output": [0], "value_inputs": []}, {"type": "filter_size", "inputs": [0], "_output": [], "value_inputs": ["small"]}, {"type": "filter_color", "inputs": [1], "_output": [], "value_inputs": ["yellow"]}, {"type": "filter_material", "inputs": [2], "_output": [], "value_inputs": ["rubber"]}, {"type": "filter_shape", "inputs": [3], "_output": [], "value_inputs": ["cube"]}, {"type": "count", "inputs": [4], "_output": 0, "value_inputs": []}], "answer": 0, "template_filename": "1obj.json", "question_family_index": 0, "question_index": 31}, {"split": "train_full", "image_filename": "CLEVR_train_full_000015.png", "image_index": 15, "image": "CLEVR_train_full_000015", "question": "small cyan rubber cylinder", "program": [{"type": "scene", "inputs": [], "_output": [0], "value_inputs": []}, {"type": "filter_size", "inputs": [0], "_output": [0], "value_inputs": ["small"]}, {"type": "filter_color", "inputs": [1], "_output": [0], "value_inputs": ["cyan"]}, {"type": "filter_material", "inputs": [2], "_output": [0], "value_inputs": ["rubber"]}, {"type": "filter_shape", "inputs": [3], "_output": [0], "value_inputs": ["cylinder"]}, {"type": "count", "inputs": [4], "_output": 1, "value_inputs": []}], "answer": 1, "template_filename": "1obj.json", "question_family_index": 0, "question_index": 32}, {"split": "train_full", "image_filename": "CLEVR_train_full_000015.png", "image_index": 15, "image": "CLEVR_train_full_000015", "question": "large red shiny ball", "program": [{"type": "scene", "inputs": [], "_output": [0], "value_inputs": []}, {"type": "filter_size", "inputs": [0], "_output": [], "value_inputs": ["large"]}, {"type": "filter_color", "inputs": [1], "_output": [], "value_inputs": ["red"]}, {"type": "filter_material", "inputs": [2], "_output": [], "value_inputs": ["metal"]}, {"type": "filter_shape", "inputs": [3], "_output": [], "value_inputs": ["sphere"]}, {"type": "count", "inputs": [4], "_output": 0, "value_inputs": []}], "answer": 0, "template_filename": "1obj.json", "question_family_index": 0, "question_index": 33}, {"split": "train_full", "image_filename": "CLEVR_train_full_000016.png", "image_index": 16, "image": "CLEVR_train_full_000016", "question": "big brown rubber ball", "program": [{"type": "scene", "inputs": [], "_output": [0], "value_inputs": []}, {"type": "filter_size", "inputs": [0], "_output": [0], "value_inputs": ["large"]}, {"type": "filter_color", "inputs": [1], "_output": [0], "value_inputs": ["brown"]}, {"type": "filter_material", "inputs": [2], "_output": [0], "value_inputs": ["rubber"]}, {"type": "filter_shape", "inputs": [3], "_output": [0], "value_inputs": ["sphere"]}, {"type": "count", "inputs": [4], "_output": 1, "value_inputs": []}], "answer": 1, "template_filename": "1obj.json", "question_family_index": 0, "question_index": 34}, {"split": "train_full", "image_filename": "CLEVR_train_full_000016.png", "image_index": 16, "image": "CLEVR_train_full_000016", "question": "large brown matte block", "program": [{"type": "scene", "inputs": [], "_output": [0], "value_inputs": []}, {"type": "filter_size", "inputs": [0], "_output": [0], "value_inputs": ["large"]}, {"type": "filter_color", "inputs": [1], "_output": [0], "value_inputs": ["brown"]}, {"type": "filter_material", "inputs": [2], "_output": [0], "value_inputs": ["rubber"]}, {"type": "filter_shape", "inputs": [3], "_output": [], "value_inputs": ["cube"]}, {"type": "count", "inputs": [4], "_output": 0, "value_inputs": []}], "answer": 0, "template_filename": "1obj.json", "question_family_index": 0, "question_index": 35}, {"split": "train_full", "image_filename": "CLEVR_train_full_000017.png", "image_index": 17, "image": "CLEVR_train_full_000017", "question": "tiny cyan metal cube", "program": [{"type": "scene", "inputs": [], "_output": [0], "value_inputs": []}, {"type": "filter_size", "inputs": [0], "_output": [0], "value_inputs": ["small"]}, {"type": "filter_color", "inputs": [1], "_output": [0], "value_inputs": ["cyan"]}, {"type": "filter_material", "inputs": [2], "_output": [0], "value_inputs": ["metal"]}, {"type": "filter_shape", "inputs": [3], "_output": [0], "value_inputs": ["cube"]}, {"type": "count", "inputs": [4], "_output": 1, "value_inputs": []}], "answer": 1, "template_filename": "1obj.json", "question_family_index": 0, "question_index": 36}, {"split": "train_full", "image_filename": "CLEVR_train_full_000017.png", "image_index": 17, "image": "CLEVR_train_full_000017", "question": "tiny cyan matte block", "program": [{"type": "scene", "inputs": [], "_output": [0], "value_inputs": []}, {"type": "filter_size", "inputs": [0], "_output": [0], "value_inputs": ["small"]}, {"type": "filter_color", "inputs": [1], "_output": [0], "value_inputs": ["cyan"]}, {"type": "filter_material", "inputs": [2], "_output": [], "value_inputs": ["rubber"]}, {"type": "filter_shape", "inputs": [3], "_output": [], "value_inputs": ["cube"]}, {"type": "count", "inputs": [4], "_output": 0, "value_inputs": []}], "answer": 0, "template_filename": "1obj.json", "question_family_index": 0, "question_index": 37}, {"split": "train_full", "image_filename": "CLEVR_train_full_000018.png", "image_index": 18, "image": "CLEVR_train_full_000018", "question": "big blue metal sphere", "program": [{"type": "scene", "inputs": [], "_output": [0], "value_inputs": []}, {"type": "filter_size", "inputs": [0], "_output": [0], "value_inputs": ["large"]}, {"type": "filter_color", "inputs": [1], "_output": [0], "value_inputs": ["blue"]}, {"type": "filter_material", "inputs": [2], "_output": [0], "value_inputs": ["metal"]}, {"type": "filter_shape", "inputs": [3], "_output": [0], "value_inputs": ["sphere"]}, {"type": "count", "inputs": [4], "_output": 1, "value_inputs": []}], "answer": 1, "template_filename": "1obj.json", "question_family_index": 0, "question_index": 38}, {"split": "train_full", "image_filename": "CLEVR_train_full_000018.png", "image_index": 18, "image": "CLEVR_train_full_000018", "question": "large red matte sphere", "program": [{"type": "scene", "inputs": [], "_output": [0], "value_inputs": []}, {"type": "filter_size", "inputs": [0], "_output": [0], "value_inputs": ["large"]}, {"type": "filter_color", "inputs": [1], "_output": [], "value_inputs": ["red"]}, {"type": "filter_material", "inputs": [2], "_output": [], "value_inputs": ["rubber"]}, {"type": "filter_shape", "inputs": [3], "_output": [], "value_inputs": ["sphere"]}, {"type": "count", "inputs": [4], "_output": 0, "value_inputs": []}], "answer": 0, "template_filename": "1obj.json", "question_family_index": 0, "question_index": 39}, {"split": "train_full", "image_filename": "CLEVR_train_full_000019.png", "image_index": 19, "image": "CLEVR_train_full_000019", "question": "big gray matte block", "program": [{"type": "scene", "inputs": [], "_output": [0], "value_inputs": []}, {"type": "filter_size", "inputs": [0], "_output": [0], "value_inputs": ["large"]}, {"type": "filter_color", "inputs": [1], "_output": [0], "value_inputs": ["gray"]}, {"type": "filter_material", "inputs": [2], "_output": [0], "value_inputs": ["rubber"]}, {"type": "filter_shape", "inputs": [3], "_output": [0], "value_inputs": ["cube"]}, {"type": "count", "inputs": [4], "_output": 1, "value_inputs": []}], "answer": 1, "template_filename": "1obj.json", "question_family_index": 0, "question_index": 40}, {"split": "train_full", "image_filename": "CLEVR_train_full_000019.png", "image_index": 19, "image": "CLEVR_train_full_000019", "question": "small red metal cylinder", "program": [{"type": "scene", "inputs": [], "_output": [0], "value_inputs": []}, {"type": "filter_size", "inputs": [0], "_output": [], "value_inputs": ["small"]}, {"type": "filter_color", "inputs": [1], "_output": [], "value_inputs": ["red"]}, {"type": "filter_material", "inputs": [2], "_output": [], "value_inputs": ["metal"]}, {"type": "filter_shape", "inputs": [3], "_output": [], "value_inputs": ["cylinder"]}, {"type": "count", "inputs": [4], "_output": 0, "value_inputs": []}], "answer": 0, "template_filename": "1obj.json", "question_family_index": 0, "question_index": 41}, {"split": "train_full", "image_filename": "CLEVR_train_full_000020.png", "image_index": 20, "image": "CLEVR_train_full_000020", "question": "big yellow metallic cylinder", "program": [{"type": "scene", "inputs": [], "_output": [0], "value_inputs": []}, {"type": "filter_size", "inputs": [0], "_output": [0], "value_inputs": ["large"]}, {"type": "filter_color", "inputs": [1], "_output": [], "value_inputs": ["yellow"]}, {"type": "filter_material", "inputs": [2], "_output": [], "value_inputs": ["metal"]}, {"type": "filter_shape", "inputs": [3], "_output": [], "value_inputs": ["cylinder"]}, {"type": "count", "inputs": [4], "_output": 0, "value_inputs": []}], "answer": 0, "template_filename": "1obj.json", "question_family_index": 0, "question_index": 42}, {"split": "train_full", "image_filename": "CLEVR_train_full_000020.png", "image_index": 20, "image": "CLEVR_train_full_000020", "question": "big purple matte block", "program": [{"type": "scene", "inputs": [], "_output": [0], "value_inputs": []}, {"type": "filter_size", "inputs": [0], "_output": [0], "value_inputs": ["large"]}, {"type": "filter_color", "inputs": [1], "_output": [0], "value_inputs": ["purple"]}, {"type": "filter_material", "inputs": [2], "_output": [0], "value_inputs": ["rubber"]}, {"type": "filter_shape", "inputs": [3], "_output": [0], "value_inputs": ["cube"]}, {"type": "count", "inputs": [4], "_output": 1, "value_inputs": []}], "answer": 1, "template_filename": "1obj.json", "question_family_index": 0, "question_index": 43}, {"split": "train_full", "image_filename": "CLEVR_train_full_000021.png", "image_index": 21, "image": "CLEVR_train_full_000021", "question": "small blue metallic cylinder", "program": [{"type": "scene", "inputs": [], "_output": [0], "value_inputs": []}, {"type": "filter_size", "inputs": [0], "_output": [0], "value_inputs": ["small"]}, {"type": "filter_color", "inputs": [1], "_output": [0], "value_inputs": ["blue"]}, {"type": "filter_material", "inputs": [2], "_output": [0], "value_inputs": ["metal"]}, {"type": "filter_shape", "inputs": [3], "_output": [], "value_inputs": ["cylinder"]}, {"type": "count", "inputs": [4], "_output": 0, "value_inputs": []}], "answer": 0, "template_filename": "1obj.json", "question_family_index": 0, "question_index": 44}, {"split": "train_full", "image_filename": "CLEVR_train_full_000021.png", "image_index": 21, "image": "CLEVR_train_full_000021", "question": "small blue metal cube", "program": [{"type": "scene", "inputs": [], "_output": [0], "value_inputs": []}, {"type": "filter_size", "inputs": [0], "_output": [0], "value_inputs": ["small"]}, {"type": "filter_color", "inputs": [1], "_output": [0], "value_inputs": ["blue"]}, {"type": "filter_material", "inputs": [2], "_output": [0], "value_inputs": ["metal"]}, {"type": "filter_shape", "inputs": [3], "_output": [0], "value_inputs": ["cube"]}, {"type": "count", "inputs": [4], "_output": 1, "value_inputs": []}], "answer": 1, "template_filename": "1obj.json", "question_family_index": 0, "question_index": 45}, {"split": "train_full", "image_filename": "CLEVR_train_full_000021.png", "image_index": 21, "image": "CLEVR_train_full_000021", "question": "big green metal cube", "program": [{"type": "scene", "inputs": [], "_output": [0], "value_inputs": []}, {"type": "filter_size", "inputs": [0], "_output": [], "value_inputs": ["large"]}, {"type": "filter_color", "inputs": [1], "_output": [], "value_inputs": ["green"]}, {"type": "filter_material", "inputs": [2], "_output": [], "value_inputs": ["metal"]}, {"type": "filter_shape", "inputs": [3], "_output": [], "value_inputs": ["cube"]}, {"type": "count", "inputs": [4], "_output": 0, "value_inputs": []}], "answer": 0, "template_filename": "1obj.json", "question_family_index": 0, "question_index": 46}, {"split": "train_full", "image_filename": "CLEVR_train_full_000022.png", "image_index": 22, "image": "CLEVR_train_full_000022", "question": "small purple metal block", "program": [{"type": "scene", "inputs": [], "_output": [0], "value_inputs": []}, {"type": "filter_size", "inputs": [0], "_output": [0], "value_inputs": ["small"]}, {"type": "filter_color", "inputs": [1], "_output": [0], "value_inputs": ["purple"]}, {"type": "filter_material", "inputs": [2], "_output": [0], "value_inputs": ["metal"]}, {"type": "filter_shape", "inputs": [3], "_output": [0], "value_inputs": ["cube"]}, {"type": "count", "inputs": [4], "_output": 1, "value_inputs": []}], "answer": 1, "template_filename": "1obj.json", "question_family_index": 0, "question_index": 47}, {"split": "train_full", "image_filename": "CLEVR_train_full_000022.png", "image_index": 22, "image": "CLEVR_train_full_000022", "question": "small red matte cylinder", "program": [{"type": "scene", "inputs": [], "_output": [0], "value_inputs": []}, {"type": "filter_size", "inputs": [0], "_output": [0], "value_inputs": ["small"]}, {"type": "filter_color", "inputs": [1], "_output": [], "value_inputs": ["red"]}, {"type": "filter_material", "inputs": [2], "_output": [], "value_inputs": ["rubber"]}, {"type": "filter_shape", "inputs": [3], "_output": [], "value_inputs": ["cylinder"]}, {"type": "count", "inputs": [4], "_output": 0, "value_inputs": []}], "answer": 0, "template_filename": "1obj.json", "question_family_index": 0, "question_index": 48}, {"split": "train_full", "image_filename": "CLEVR_train_full_000023.png", "image_index": 23, "image": "CLEVR_train_full_000023", "question": "large green shiny block", "program": [{"type": "scene", "inputs": [], "_output": [0], "value_inputs": []}, {"type": "filter_size", "inputs": [0], "_output": [0], "value_inputs": ["large"]}, {"type": "filter_color", "inputs": [1], "_output": [0], "value_inputs": ["green"]}, {"type": "filter_material", "inputs": [2], "_output": [0], "value_inputs": ["metal"]}, {"type": "filter_shape", "inputs": [3], "_output": [0], "value_inputs": ["cube"]}, {"type": "count", "inputs": [4], "_output": 1, "value_inputs": []}], "answer": 1, "template_filename": "1obj.json", "question_family_index": 0, "question_index": 49}, {"split": "train_full", "image_filename": "CLEVR_train_full_000024.png", "image_index": 24, "image": "CLEVR_train_full_000024", "question": "large yellow rubber cylinder", "program": [{"type": "scene", "inputs": [], "_output": [0], "value_inputs": []}, {"type": "filter_size", "inputs": [0], "_output": [0], "value_inputs": ["large"]}, {"type": "filter_color", "inputs": [1], "_output": [0], "value_inputs": ["yellow"]}, {"type": "filter_material", "inputs": [2], "_output": [0], "value_inputs": ["rubber"]}, {"type": "filter_shape", "inputs": [3], "_output": [0], "value_inputs": ["cylinder"]}, {"type": "count", "inputs": [4], "_output": 1, "value_inputs": []}], "answer": 1, "template_filename": "1obj.json", "question_family_index": 0, "question_index": 50}, {"split": "train_full", "image_filename": "CLEVR_train_full_000025.png", "image_index": 25, "image": "CLEVR_train_full_000025", "question": "tiny blue rubber sphere", "program": [{"type": "scene", "inputs": [], "_output": [0], "value_inputs": []}, {"type": "filter_size", "inputs": [0], "_output": [0], "value_inputs": ["small"]}, {"type": "filter_color", "inputs": [1], "_output": [0], "value_inputs": ["blue"]}, {"type": "filter_material", "inputs": [2], "_output": [0], "value_inputs": ["rubber"]}, {"type": "filter_shape", "inputs": [3], "_output": [0], "value_inputs": ["sphere"]}, {"type": "count", "inputs": [4], "_output": 1, "value_inputs": []}], "answer": 1, "template_filename": "1obj.json", "question_family_index": 0, "question_index": 51}, {"split": "train_full", "image_filename": "CLEVR_train_full_000100.png", "image_index": 100, "image": "CLEVR_train_full_000100", "question": "small red metallic cube", "program": [{"type": "scene", "inputs": [], "_output": [0], "value_inputs": []}, {"type": "filter_size", "inputs": [0], "_output": [], "value_inputs": ["small"]}, {"type": "filter_color", "inputs": [1], "_output": [], "value_inputs": ["red"]}, {"type": "filter_material", "inputs": [2], "_output": [], "value_inputs": ["metal"]}, {"type": "filter_shape", "inputs": [3], "_output": [], "value_inputs": ["cube"]}, {"type": "count", "inputs": [4], "_output": 0, "value_inputs": []}], "answer": 0, "template_filename": "1obj.json", "question_family_index": 0, "question_index": 52}, {"split": "train_full", "image_filename": "CLEVR_train_full_000100.png", "image_index": 100, "image": "CLEVR_train_full_000100", "question": "large brown matte block", "program": [{"type": "scene", "inputs": [], "_output": [0], "value_inputs": []}, {"type": "filter_size", "inputs": [0], "_output": [0], "value_inputs": ["large"]}, {"type": "filter_color", "inputs": [1], "_output": [0], "value_inputs": ["brown"]}, {"type": "filter_material", "inputs": [2], "_output": [0], "value_inputs": ["rubber"]}, {"type": "filter_shape", "inputs": [3], "_output": [0], "value_inputs": ["cube"]}, {"type": "count", "inputs": [4], "_output": 1, "value_inputs": []}], "answer": 1, "template_filename": "1obj.json", "question_family_index": 0, "question_index": 53}, {"split": "train_full", "image_filename": "CLEVR_train_full_000100.png", "image_index": 100, "image": "CLEVR_train_full_000100", "question": "tiny gray metallic cube", "program": [{"type": "scene", "inputs": [], "_output": [0], "value_inputs": []}, {"type": "filter_size", "inputs": [0], "_output": [], "value_inputs": ["small"]}, {"type": "filter_color", "inputs": [1], "_output": [], "value_inputs": ["gray"]}, {"type": "filter_material", "inputs": [2], "_output": [], "value_inputs": ["metal"]}, {"type": "filter_shape", "inputs": [3], "_output": [], "value_inputs": ["cube"]}, {"type": "count", "inputs": [4], "_output": 0, "value_inputs": []}], "answer": 0, "template_filename": "1obj.json", "question_family_index": 0, "question_index": 54}, {"split": "train_full", "image_filename": "CLEVR_train_full_000101.png", "image_index": 101, "image": "CLEVR_train_full_000101", "question": "tiny blue metallic ball", "program": [{"type": "scene", "inputs": [], "_output": [0], "value_inputs": []}, {"type": "filter_size", "inputs": [0], "_output": [0], "value_inputs": ["small"]}, {"type": "filter_color", "inputs": [1], "_output": [0], "value_inputs": ["blue"]}, {"type": "filter_material", "inputs": [2], "_output": [0], "value_inputs": ["metal"]}, {"type": "filter_shape", "inputs": [3], "_output": [0], "value_inputs": ["sphere"]}, {"type": "count", "inputs": [4], "_output": 1, "value_inputs": []}], "answer": 1, "template_filename": "1obj.json", "question_family_index": 0, "question_index": 55}, {"split": "train_full", "image_filename": "CLEVR_train_full_000101.png", "image_index": 101, "image": "CLEVR_train_full_000101", "question": "tiny gray rubber cylinder", "program": [{"type": "scene", "inputs": [], "_output": [0], "value_inputs": []}, {"type": "filter_size", "inputs": [0], "_output": [0], "value_inputs": ["small"]}, {"type": "filter_color", "inputs": [1], "_output": [], "value_inputs": ["gray"]}, {"type": "filter_material", "inputs": [2], "_output": [], "value_inputs": ["rubber"]}, {"type": "filter_shape", "inputs": [3], "_output": [], "value_inputs": ["cylinder"]}, {"type": "count", "inputs": [4], "_output": 0, "value_inputs": []}], "answer": 0, "template_filename": "1obj.json", "question_family_index": 0, "question_index": 56}, {"split": "train_full", "image_filename": "CLEVR_train_full_000102.png", "image_index": 102, "image": "CLEVR_train_full_000102", "question": "small blue shiny cylinder", "program": [{"type": "scene", "inputs": [], "_output": [0], "value_inputs": []}, {"type": "filter_size", "inputs": [0], "_output": [0], "value_inputs": ["small"]}, {"type": "filter_color", "inputs": [1], "_output": [0], "value_inputs": ["blue"]}, {"type": "filter_material", "inputs": [2], "_output": [0], "value_inputs": ["metal"]}, {"type": "filter_shape", "inputs": [3], "_output": [0], "value_inputs": ["cylinder"]}, {"type": "count", "inputs": [4], "_output": 1, "value_inputs": []}], "answer": 1, "template_filename": "1obj.json", "question_family_index": 0, "question_index": 57}, {"split": "train_full", "image_filename": "CLEVR_train_full_000102.png", "image_index": 102, "image": "CLEVR_train_full_000102", "question": "small cyan shiny ball", "program": [{"type": "scene", "inputs": [], "_output": [0], "value_inputs": []}, {"type": "filter_size", "inputs": [0], "_output": [0], "value_inputs": ["small"]}, {"type": "filter_color", "inputs": [1], "_output": [], "value_inputs": ["cyan"]}, {"type": "filter_material", "inputs": [2], "_output": [], "value_inputs": ["metal"]}, {"type": "filter_shape", "inputs": [3], "_output": [], "value_inputs": ["sphere"]}, {"type": "count", "inputs": [4], "_output": 0, "value_inputs": []}], "answer": 0, "template_filename": "1obj.json", "question_family_index": 0, "question_index": 58}, {"split": "train_full", "image_filename": "CLEVR_train_full_000103.png", "image_index": 103, "image": "CLEVR_train_full_000103", "question": "tiny purple rubber cylinder", "program": [{"type": "scene", "inputs": [], "_output": [0], "value_inputs": []}, {"type": "filter_size", "inputs": [0], "_output": [0], "value_inputs": ["small"]}, {"type": "filter_color", "inputs": [1], "_output": [0], "value_inputs": ["purple"]}, {"type": "filter_material", "inputs": [2], "_output": [0], "value_inputs": ["rubber"]}, {"type": "filter_shape", "inputs": [3], "_output": [0], "value_inputs": ["cylinder"]}, {"type": "count", "inputs": [4], "_output": 1, "value_inputs": []}], "answer": 1, "template_filename": "1obj.json", "question_family_index": 0, "question_index": 59}, {"split": "train_full", "image_filename": "CLEVR_train_full_000103.png", "image_index": 103, "image": "CLEVR_train_full_000103", "question": "large red rubber block", "program": [{"type": "scene", "inputs": [], "_output": [0], "value_inputs": []}, {"type": "filter_size", "inputs": [0], "_output": [], "value_inputs": ["large"]}, {"type": "filter_color", "inputs": [1], "_output": [], "value_inputs": ["red"]}, {"type": "filter_material", "inputs": [2], "_output": [], "value_inputs": ["rubber"]}, {"type": "filter_shape", "inputs": [3], "_output": [], "value_inputs": ["cube"]}, {"type": "count", "inputs": [4], "_output": 0, "value_inputs": []}], "answer": 0, "template_filename": "1obj.json", "question_family_index": 0, "question_index": 60}, {"split": "train_full", "image_filename": "CLEVR_train_full_000104.png", "image_index": 104, "image": "CLEVR_train_full_000104", "question": "big yellow matte sphere", "program": [{"type": "scene", "inputs": [], "_output": [0], "value_inputs": []}, {"type": "filter_size", "inputs": [0], "_output": [0], "value_inputs": ["large"]}, {"type": "filter_color", "inputs": [1], "_output": [0], "value_inputs": ["yellow"]}, {"type": "filter_material", "inputs": [2], "_output": [0], "value_inputs": ["rubber"]}, {"type": "filter_shape", "inputs": [3], "_output": [0], "value_inputs": ["sphere"]}, {"type": "count", "inputs": [4], "_output": 1, "value_inputs": []}], "answer": 1, "template_filename": "1obj.json", "question_family_index": 0, "question_index": 61}, {"split": "train_full", "image_filename": "CLEVR_train_full_000104.png", "image_index": 104, "image": "CLEVR_train_full_000104", "question": "big green metal cylinder", "program": [{"type": "scene", "inputs": [], "_output": [0], "value_inputs": []}, {"type": "filter_size", "inputs": [0], "_output": [0], "value_inputs": ["large"]}, {"type": "filter_color", "inputs": [1], "_output": [], "value_inputs": ["green"]}, {"type": "filter_material", "inputs": [2], "_output": [], "value_inputs": ["metal"]}, {"type": "filter_shape", "inputs": [3], "_output": [], "value_inputs": ["cylinder"]}, {"type": "count", "inputs": [4], "_output": 0, "value_inputs": []}], "answer": 0, "template_filename": "1obj.json", "question_family_index": 0, "question_index": 62}, {"split": "train_full", "image_filename": "CLEVR_train_full_000105.png", "image_index": 105, "image": "CLEVR_train_full_000105", "question": "small yellow matte cube", "program": [{"type": "scene", "inputs": [], "_output": [0], "value_inputs": []}, {"type": "filter_size", "inputs": [0], "_output": [0], "value_inputs": ["small"]}, {"type": "filter_color", "inputs": [1], "_output": [0], "value_inputs": ["yellow"]}, {"type": "filter_material", "inputs": [2], "_output": [0], "value_inputs": ["rubber"]}, {"type": "filter_shape", "inputs": [3], "_output": [0], "value_inputs": ["cube"]}, {"type": "count", "inputs": [4], "_output": 1, "value_inputs": []}], "answer": 1, "template_filename": "1obj.json", "question_family_index": 0, "question_index": 63}, {"split": "train_full", "image_filename": "CLEVR_train_full_000105.png", "image_index": 105, "image": "CLEVR_train_full_000105", "question": "small blue rubber cube", "program": [{"type": "scene", "inputs": [], "_output": [0], "value_inputs": []}, {"type": "filter_size", "inputs": [0], "_output": [0], "value_inputs": ["small"]}, {"type": "filter_color", "inputs": [1], "_output": [], "value_inputs": ["blue"]}, {"type": "filter_material", "inputs": [2], "_output": [], "value_inputs": ["rubber"]}, {"type": "filter_shape", "inputs": [3], "_output": [], "value_inputs": ["cube"]}, {"type": "count", "inputs": [4], "_output": 0, "value_inputs": []}], "answer": 0, "template_filename": "1obj.json", "question_family_index": 0, "question_index": 64}, {"split": "train_full", "image_filename": "CLEVR_train_full_000106.png", "image_index": 106, "image": "CLEVR_train_full_000106", "question": "large green metallic sphere", "program": [{"type": "scene", "inputs": [], "_output": [0], "value_inputs": []}, {"type": "filter_size", "inputs": [0], "_output": [0], "value_inputs": ["large"]}, {"type": "filter_color", "inputs": [1], "_output": [0], "value_inputs": ["green"]}, {"type": "filter_material", "inputs": [2], "_output": [0], "value_inputs": ["metal"]}, {"type": "filter_shape", "inputs": [3], "_output": [0], "value_inputs": ["sphere"]}, {"type": "count", "inputs": [4], "_output": 1, "value_inputs": []}], "answer": 1, "template_filename": "1obj.json", "question_family_index": 0, "question_index": 65}, {"split": "train_full", "image_filename": "CLEVR_train_full_000106.png", "image_index": 106, "image": "CLEVR_train_full_000106", "question": "small brown matte ball", "program": [{"type": "scene", "inputs": [], "_output": [0], "value_inputs": []}, {"type": "filter_size", "inputs": [0], "_output": [], "value_inputs": ["small"]}, {"type": "filter_color", "inputs": [1], "_output": [], "value_inputs": ["brown"]}, {"type": "filter_material", "inputs": [2], "_output": [], "value_inputs": ["rubber"]}, {"type": "filter_shape", "inputs": [3], "_output": [], "value_inputs": ["sphere"]}, {"type": "count", "inputs": [4], "_output": 0, "value_inputs": []}], "answer": 0, "template_filename": "1obj.json", "question_family_index": 0, "question_index": 66}, {"split": "train_full", "image_filename": "CLEVR_train_full_000107.png", "image_index": 107, "image": "CLEVR_train_full_000107", "question": "tiny blue metal cube", "program": [{"type": "scene", "inputs": [], "_output": [0], "value_inputs": []}, {"type": "filter_size", "inputs": [0], "_output": [0], "value_inputs": ["small"]}, {"type": "filter_color", "inputs": [1], "_output": [0], "value_inputs": ["blue"]}, {"type": "filter_material", "inputs": [2], "_output": [0], "value_inputs": ["metal"]}, {"type": "filter_shape", "inputs": [3], "_output": [0], "value_inputs": ["cube"]}, {"type": "count", "inputs": [4], "_output": 1, "value_inputs": []}], "answer": 1, "template_filename": "1obj.json", "question_family_index": 0, "question_index": 67}, {"split": "train_full", "image_filename": "CLEVR_train_full_000107.png", "image_index": 107, "image": "CLEVR_train_full_000107", "question": "large purple metallic ball", "program": [{"type": "scene", "inputs": [], "_output": [0], "value_inputs": []}, {"type": "filter_size", "inputs": [0], "_output": [], "value_inputs": ["large"]}, {"type": "filter_color", "inputs": [1], "_output": [], "value_inputs": ["purple"]}, {"type": "filter_material", "inputs": [2], "_output": [], "value_inputs": ["metal"]}, {"type": "filter_shape", "inputs": [3], "_output": [], "value_inputs": ["sphere"]}, {"type": "count", "inputs": [4], "_output": 0, "value_inputs": []}], "answer": 0, "template_filename": "1obj.json", "question_family_index": 0, "question_index": 68}, {"split": "train_full", "image_filename": "CLEVR_train_full_000108.png", "image_index": 108, "image": "CLEVR_train_full_000108", "question": "small green rubber cylinder", "program": [{"type": "scene", "inputs": [], "_output": [0], "value_inputs": []}, {"type": "filter_size", "inputs": [0], "_output": [0], "value_inputs": ["small"]}, {"type": "filter_color", "inputs": [1], "_output": [0], "value_inputs": ["green"]}, {"type": "filter_material", "inputs": [2], "_output": [0], "value_inputs": ["rubber"]}, {"type": "filter_shape", "inputs": [3], "_output": [0], "value_inputs": ["cylinder"]}, {"type": "count", "inputs": [4], "_output": 1, "value_inputs": []}], "answer": 1, "template_filename": "1obj.json", "question_family_index": 0, "question_index": 69}, {"split": "train_full", "image_filename": "CLEVR_train_full_000108.png", "image_index": 108, "image": "CLEVR_train_full_000108", "question": "big brown rubber ball", "program": [{"type": "scene", "inputs": [], "_output": [0], "value_inputs": []}, {"type": "filter_size", "inputs": [0], "_output": [], "value_inputs": ["large"]}, {"type": "filter_color", "inputs": [1], "_output": [], "value_inputs": ["brown"]}, {"type": "filter_material", "inputs": [2], "_output": [], "value_inputs": ["rubber"]}, {"type": "filter_shape", "inputs": [3], "_output": [], "value_inputs": ["sphere"]}, {"type": "count", "inputs": [4], "_output": 0, "value_inputs": []}], "answer": 0, "template_filename": "1obj.json", "question_family_index": 0, "question_index": 70}, {"split": "train_full", "image_filename": "CLEVR_train_full_000109.png", "image_index": 109, "image": "CLEVR_train_full_000109", "question": "tiny gray rubber cylinder", "program": [{"type": "scene", "inputs": [], "_output": [0], "value_inputs": []}, {"type": "filter_size", "inputs": [0], "_output": [0], "value_inputs": ["small"]}, {"type": "filter_color", "inputs": [1], "_output": [0], "value_inputs": ["gray"]}, {"type": "filter_material", "inputs": [2], "_output": [0], "value_inputs": ["rubber"]}, {"type": "filter_shape", "inputs": [3], "_output": [0], "value_inputs": ["cylinder"]}, {"type": "count", "inputs": [4], "_output": 1, "value_inputs": []}], "answer": 1, "template_filename": "1obj.json", "question_family_index": 0, "question_index": 71}, {"split": "train_full", "image_filename": "CLEVR_train_full_000110.png", "image_index": 110, "image": "CLEVR_train_full_000110", "question": "small gray metal cube", "program": [{"type": "scene", "inputs": [], "_output": [0], "value_inputs": []}, {"type": "filter_size", "inputs": [0], "_output": [], "value_inputs": ["small"]}, {"type": "filter_color", "inputs": [1], "_output": [], "value_inputs": ["gray"]}, {"type": "filter_material", "inputs": [2], "_output": [], "value_inputs": ["metal"]}, {"type": "filter_shape", "inputs": [3], "_output": [], "value_inputs": ["cube"]}, {"type": "count", "inputs": [4], "_output": 0, "value_inputs": []}], "answer": 0, "template_filename": "1obj.json", "question_family_index": 0, "question_index": 72}, {"split": "train_full", "image_filename": "CLEVR_train_full_000110.png", "image_index": 110, "image": "CLEVR_train_full_000110", "question": "large green rubber block", "program": [{"type": "scene", "inputs": [], "_output": [0], "value_inputs": []}, {"type": "filter_size", "inputs": [0], "_output": [0], "value_inputs": ["large"]}, {"type": "filter_color", "inputs": [1], "_output": [], "value_inputs": ["green"]}, {"type": "filter_material", "inputs": [2], "_output": [], "value_inputs": ["rubber"]}, {"type": "filter_shape", "inputs": [3], "_output": [], "value_inputs": ["cube"]}, {"type": "count", "inputs": [4], "_output": 0, "value_inputs": []}], "answer": 0, "template_filename": "1obj.json", "question_family_index": 0, "question_index": 73}, {"split": "train_full", "image_filename": "CLEVR_train_full_000110.png", "image_index": 110, "image": "CLEVR_train_full_000110", "question": "large brown shiny block", "program": [{"type": "scene", "inputs": [], "_output": [0], "value_inputs": []}, {"type": "filter_size", "inputs": [0], "_output": [0], "value_inputs": ["large"]}, {"type": "filter_color", "inputs": [1], "_output": [0], "value_inputs": ["brown"]}, {"type": "filter_material", "inputs": [2], "_output": [0], "value_inputs": ["metal"]}, {"type": "filter_shape", "inputs": [3], "_output": [0], "value_inputs": ["cube"]}, {"type": "count", "inputs": [4], "_output": 1, "value_inputs": []}], "answer": 1, "template_filename": "1obj.json", "question_family_index": 0, "question_index": 74}, {"split": "train_full", "image_filename": "CLEVR_train_full_000111.png", "image_index": 111, "image": "CLEVR_train_full_000111", "question": "big brown rubber block", "program": [{"type": "scene", "inputs": [], "_output": [0], "value_inputs": []}, {"type": "filter_size", "inputs": [0], "_output": [0], "value_inputs": ["large"]}, {"type": "filter_color", "inputs": [1], "_output": [0], "value_inputs": ["brown"]}, {"type": "filter_material", "inputs": [2], "_output": [0], "value_inputs": ["rubber"]}, {"type": "filter_shape", "inputs": [3], "_output": [0], "value_inputs": ["cube"]}, {"type": "count", "inputs": [4], "_output": 1, "value_inputs": []}], "answer": 1, "template_filename": "1obj.json", "question_family_index": 0, "question_index": 75}, {"split": "train_full", "image_filename": "CLEVR_train_full_000111.png", "image_index": 111, "image": "CLEVR_train_full_000111", "question": "large green metal sphere", "program": [{"type": "scene", "inputs": [], "_output": [0], "value_inputs": []}, {"type": "filter_size", "inputs": [0], "_output": [0], "value_inputs": ["large"]}, {"type": "filter_color", "inputs": [1], "_output": [], "value_inputs": ["green"]}, {"type": "filter_material", "inputs": [2], "_output": [], "value_inputs": ["metal"]}, {"type": "filter_shape", "inputs": [3], "_output": [], "value_inputs": ["sphere"]}, {"type": "count", "inputs": [4], "_output": 0, "value_inputs": []}], "answer": 0, "template_filename": "1obj.json", "question_family_index": 0, "question_index": 76}, {"split": "train_full", "image_filename": "CLEVR_train_full_000111.png", "image_index": 111, "image": "CLEVR_train_full_000111", "question": "big cyan metallic cylinder", "program": [{"type": "scene", "inputs": [], "_output": [0], "value_inputs": []}, {"type": "filter_size", "inputs": [0], "_output": [0], "value_inputs": ["large"]}, {"type": "filter_color", "inputs": [1], "_output": [], "value_inputs": ["cyan"]}, {"type": "filter_material", "inputs": [2], "_output": [], "value_inputs": ["metal"]}, {"type": "filter_shape", "inputs": [3], "_output": [], "value_inputs": ["cylinder"]}, {"type": "count", "inputs": [4], "_output": 0, "value_inputs": []}], "answer": 0, "template_filename": "1obj.json", "question_family_index": 0, "question_index": 77}, {"split": "train_full", "image_filename": "CLEVR_train_full_000112.png", "image_index": 112, "image": "CLEVR_train_full_000112", "question": "big yellow metallic block", "program": [{"type": "scene", "inputs": [], "_output": [0], "value_inputs": []}, {"type": "filter_size", "inputs": [0], "_output": [0], "value_inputs": ["large"]}, {"type": "filter_color", "inputs": [1], "_output": [0], "value_inputs": ["yellow"]}, {"type": "filter_material", "inputs": [2], "_output": [0], "value_inputs": ["metal"]}, {"type": "filter_shape", "inputs": [3], "_output": [0], "value_inputs": ["cube"]}, {"type": "count", "inputs": [4], "_output": 1, "value_inputs": []}], "answer": 1, "template_filename": "1obj.json", "question_family_index": 0, "question_index": 78}, {"split": "train_full", "image_filename": "CLEVR_train_full_000112.png", "image_index": 112, "image": "CLEVR_train_full_000112", "question": "small purple shiny ball", "program": [{"type": "scene", "inputs": [], "_output": [0], "value_inputs": []}, {"type": "filter_size", "inputs": [0], "_output": [], "value_inputs": ["small"]}, {"type": "filter_color", "inputs": [1], "_output": [], "value_inputs": ["purple"]}, {"type": "filter_material", "inputs": [2], "_output": [], "value_inputs": ["metal"]}, {"type": "filter_shape", "inputs": [3], "_output": [], "value_inputs": ["sphere"]}, {"type": "count", "inputs": [4], "_output": 0, "value_inputs": []}], "answer": 0, "template_filename": "1obj.json", "question_family_index": 0, "question_index": 79}, {"split": "train_full", "image_filename": "CLEVR_train_full_000113.png", "image_index": 113, "image": "CLEVR_train_full_000113", "question": "tiny yellow metallic cube", "program": [{"type": "scene", "inputs": [], "_output": [0], "value_inputs": []}, {"type": "filter_size", "inputs": [0], "_output": [0], "value_inputs": ["small"]}, {"type": "filter_color", "inputs": [1], "_output": [0], "value_inputs": ["yellow"]}, {"type": "filter_material", "inputs": [2], "_output": [0], "value_inputs": ["metal"]}, {"type": "filter_shape", "inputs": [3], "_output": [0], "value_inputs": ["cube"]}, {"type": "count", "inputs": [4], "_output": 1, "value_inputs": []}], "answer": 1, "template_filename": "1obj.json", "question_family_index": 0, "question_index": 80}, {"split": "train_full", "image_filename": "CLEVR_train_full_000113.png", "image_index": 113, "image": "CLEVR_train_full_000113", "question": "tiny red shiny cylinder", "program": [{"type": "scene", "inputs": [], "_output": [0], "value_inputs": []}, {"type": "filter_size", "inputs": [0], "_output": [0], "value_inputs": ["small"]}, {"type": "filter_color", "inputs": [1], "_output": [], "value_inputs": ["red"]}, {"type": "filter_material", "inputs": [2], "_output": [], "value_inputs": ["metal"]}, {"type": "filter_shape", "inputs": [3], "_output": [], "value_inputs": ["cylinder"]}, {"type": "count", "inputs": [4], "_output": 0, "value_inputs": []}], "answer": 0, "template_filename": "1obj.json", "question_family_index": 0, "question_index": 81}, {"split": "train_full", "image_filename": "CLEVR_train_full_000114.png", "image_index": 114, "image": "CLEVR_train_full_000114", "question": "large gray rubber ball", "program": [{"type": "scene", "inputs": [], "_output": [0], "value_inputs": []}, {"type": "filter_size", "inputs": [0], "_output": [0], "value_inputs": ["large"]}, {"type": "filter_color", "inputs": [1], "_output": [0], "value_inputs": ["gray"]}, {"type": "filter_material", "inputs": [2], "_output": [0], "value_inputs": ["rubber"]}, {"type": "filter_shape", "inputs": [3], "_output": [0], "value_inputs": ["sphere"]}, {"type": "count", "inputs": [4], "_output": 1, "value_inputs": []}], "answer": 1, "template_filename": "1obj.json", "question_family_index": 0, "question_index": 82}, {"split": "train_full", "image_filename": "CLEVR_train_full_000114.png", "image_index": 114, "image": "CLEVR_train_full_000114", "question": "tiny blue rubber cylinder", "program": [{"type": "scene", "inputs": [], "_output": [0], "value_inputs": []}, {"type": "filter_size", "inputs": [0], "_output": [], "value_inputs": ["small"]}, {"type": "filter_color", "inputs": [1], "_output": [], "value_inputs": ["blue"]}, {"type": "filter_material", "inputs": [2], "_output": [], "value_inputs": ["rubber"]}, {"type": "filter_shape", "inputs": [3], "_output": [], "value_inputs": ["cylinder"]}, {"type": "count", "inputs": [4], "_output": 0, "value_inputs": []}], "answer": 0, "template_filename": "1obj.json", "question_family_index": 0, "question_index": 83}, {"split": "train_full", "image_filename": "CLEVR_train_full_000115.png", "image_index": 115, "image": "CLEVR_train_full_000115", "question": "small red matte cylinder", "program": [{"type": "scene", "inputs": [], "_output": [0], "value_inputs": []}, {"type": "filter_size", "inputs": [0], "_output": [0], "value_inputs": ["small"]}, {"type": "filter_color", "inputs": [1], "_output": [0], "value_inputs": ["red"]}, {"type": "filter_material", "inputs": [2], "_output": [0], "value_inputs": ["rubber"]}, {"type": "filter_shape", "inputs": [3], "_output": [0], "value_inputs": ["cylinder"]}, {"type": "count", "inputs": [4], "_output": 1, "value_inputs": []}], "answer": 1, "template_filename": "1obj.json", "question_family_index": 0, "question_index": 84}, {"split": "train_full", "image_filename": "CLEVR_train_full_000115.png", "image_index": 115, "image": "CLEVR_train_full_000115", "question": "small green metal block", "program": [{"type": "scene", "inputs": [], "_output": [0], "value_inputs": []}, {"type": "filter_size", "inputs": [0], "_output": [0], "value_inputs": ["small"]}, {"type": "filter_color", "inputs": [1], "_output": [], "value_inputs": ["green"]}, {"type": "filter_material", "inputs": [2], "_output": [], "value_inputs": ["metal"]}, {"type": "filter_shape", "inputs": [3], "_output": [], "value_inputs": ["cube"]}, {"type": "count", "inputs": [4], "_output": 0, "value_inputs": []}], "answer": 0, "template_filename": "1obj.json", "question_family_index": 0, "question_index": 85}, {"split": "train_full", "image_filename": "CLEVR_train_full_000116.png", "image_index": 116, "image": "CLEVR_train_full_000116", "question": "large yellow metallic cube", "program": [{"type": "scene", "inputs": [], "_output": [0], "value_inputs": []}, {"type": "filter_size", "inputs": [0], "_output": [0], "value_inputs": ["large"]}, {"type": "filter_color", "inputs": [1], "_output": [0], "value_inputs": ["yellow"]}, {"type": "filter_material", "inputs": [2], "_output": [0], "value_inputs": ["metal"]}, {"type": "filter_shape", "inputs": [3], "_output": [0], "value_inputs": ["cube"]}, {"type": "count", "inputs": [4], "_output": 1, "value_inputs": []}], "answer": 1, "template_filename": "1obj.json", "question_family_index": 0, "question_index": 86}, {"split": "train_full", "image_filename": "CLEVR_train_full_000116.png", "image_index": 116, "image": "CLEVR_train_full_000116", "question": "big brown rubber cylinder", "program": [{"type": "scene", "inputs": [], "_output": [0], "value_inputs": []}, {"type": "filter_size", "inputs": [0], "_output": [0], "value_inputs": ["large"]}, {"type": "filter_color", "inputs": [1], "_output": [], "value_inputs": ["brown"]}, {"type": "filter_material", "inputs": [2], "_output": [], "value_inputs": ["rubber"]}, {"type": "filter_shape", "inputs": [3], "_output": [], "value_inputs": ["cylinder"]}, {"type": "count", "inputs": [4], "_output": 0, "value_inputs": []}], "answer": 0, "template_filename": "1obj.json", "question_family_index": 0, "question_index": 87}, {"split": "train_full", "image_filename": "CLEVR_train_full_000117.png", "image_index": 117, "image": "CLEVR_train_full_000117", "question": "big blue matte cube", "program": [{"type": "scene", "inputs": [], "_output": [0], "value_inputs": []}, {"type": "filter_size", "inputs": [0], "_output": [0], "value_inputs": ["large"]}, {"type": "filter_color", "inputs": [1], "_output": [0], "value_inputs": ["blue"]}, {"type": "filter_material", "inputs": [2], "_output": [0], "value_inputs": ["rubber"]}, {"type": "filter_shape", "inputs": [3], "_output": [0], "value_inputs": ["cube"]}, {"type": "count", "inputs": [4], "_output": 1, "value_inputs": []}], "answer": 1, "template_filename": "1obj.json", "question_family_index": 0, "question_index": 88}, {"split": "train_full", "image_filename": "CLEVR_train_full_000118.png", "image_index": 118, "image": "CLEVR_train_full_000118", "question": "tiny red rubber cylinder", "program": [{"type": "scene", "inputs": [], "_output": [0], "value_inputs": []}, {"type": "filter_size", "inputs": [0], "_output": [0], "value_inputs": ["small"]}, {"type": "filter_color", "inputs": [1], "_output": [0], "value_inputs": ["red"]}, {"type": "filter_material", "inputs": [2], "_output": [], "value_inputs": ["rubber"]}, {"type": "filter_shape", "inputs": [3], "_output": [], "value_inputs": ["cylinder"]}, {"type": "count", "inputs": [4], "_output": 0, "value_inputs": []}], "answer": 0, "template_filename": "1obj.json", "question_family_index": 0, "question_index": 89}, {"split": "train_full", "image_filename": "CLEVR_train_full_000118.png", "image_index": 118, "image": "CLEVR_train_full_000118", "question": "small red metal cylinder", "program": [{"type": "scene", "inputs": [], "_output": [0], "value_inputs": []}, {"type": "filter_size", "inputs": [0], "_output": [0], "value_inputs": ["small"]}, {"type": "filter_color", "inputs": [1], "_output": [0], "value_inputs": ["red"]}, {"type": "filter_material", "inputs": [2], "_output": [0], "value_inputs": ["metal"]}, {"type": "filter_shape", "inputs": [3], "_output": [0], "value_inputs": ["cylinder"]}, {"type": "count", "inputs": [4], "_output": 1, "value_inputs": []}], "answer": 1, "template_filename": "1obj.json", "question_family_index": 0, "question_index": 90}, {"split": "train_full", "image_filename": "CLEVR_train_full_000118.png", "image_index": 118, "image": "CLEVR_train_full_000118", "question": "big blue rubber cylinder", "program": [{"type": "scene", "inputs": [], "_output": [0], "value_inputs": []}, {"type": "filter_size", "inputs": [0], "_output": [], "value_inputs": ["large"]}, {"type": "filter_color", "inputs": [1], "_output": [], "value_inputs": ["blue"]}, {"type": "filter_material", "inputs": [2], "_output": [], "value_inputs": ["rubber"]}, {"type": "filter_shape", "inputs": [3], "_output": [], "value_inputs": ["cylinder"]}, {"type": "count", "inputs": [4], "_output": 0, "value_inputs": []}], "answer": 0, "template_filename": "1obj.json", "question_family_index": 0, "question_index": 91}, {"split": "train_full", "image_filename": "CLEVR_train_full_000119.png", "image_index": 119, "image": "CLEVR_train_full_000119", "question": "small gray shiny cube", "program": [{"type": "scene", "inputs": [], "_output": [0], "value_inputs": []}, {"type": "filter_size", "inputs": [0], "_output": [0], "value_inputs": ["small"]}, {"type": "filter_color", "inputs": [1], "_output": [0], "value_inputs": ["gray"]}, {"type": "filter_material", "inputs": [2], "_output": [0], "value_inputs": ["metal"]}, {"type": "filter_shape", "inputs": [3], "_output": [0], "value_inputs": ["cube"]}, {"type": "count", "inputs": [4], "_output": 1, "value_inputs": []}], "answer": 1, "template_filename": "1obj.json", "question_family_index": 0, "question_index": 92}, {"split": "train_full", "image_filename": "CLEVR_train_full_000119.png", "image_index": 119, "image": "CLEVR_train_full_000119", "question": "tiny red shiny cylinder", "program": [{"type": "scene", "inputs": [], "_output": [0], "value_inputs": []}, {"type": "filter_size", "inputs": [0], "_output": [0], "value_inputs": ["small"]}, {"type": "filter_color", "inputs": [1], "_output": [], "value_inputs": ["red"]}, {"type": "filter_material", "inputs": [2], "_output": [], "value_inputs": ["metal"]}, {"type": "filter_shape", "inputs": [3], "_output": [], "value_inputs": ["cylinder"]}, {"type": "count", "inputs": [4], "_output": 0, "value_inputs": []}], "answer": 0, "template_filename": "1obj.json", "question_family_index": 0, "question_index": 93}, {"split": "train_full", "image_filename": "CLEVR_train_full_000119.png", "image_index": 119, "image": "CLEVR_train_full_000119", "question": "large gray rubber cylinder", "program": [{"type": "scene", "inputs": [], "_output": [0], "value_inputs": []}, {"type": "filter_size", "inputs": [0], "_output": [], "value_inputs": ["large"]}, {"type": "filter_color", "inputs": [1], "_output": [], "value_inputs": ["gray"]}, {"type": "filter_material", "inputs": [2], "_output": [], "value_inputs": ["rubber"]}, {"type": "filter_shape", "inputs": [3], "_output": [], "value_inputs": ["cylinder"]}, {"type": "count", "inputs": [4], "_output": 0, "value_inputs": []}], "answer": 0, "template_filename": "1obj.json", "question_family_index": 0, "question_index": 94}, {"split": "train_full", "image_filename": "CLEVR_train_full_000120.png", "image_index": 120, "image": "CLEVR_train_full_000120", "question": "big green metallic cube", "program": [{"type": "scene", "inputs": [], "_output": [0], "value_inputs": []}, {"type": "filter_size", "inputs": [0], "_output": [0], "value_inputs": ["large"]}, {"type": "filter_color", "inputs": [1], "_output": [0], "value_inputs": ["green"]}, {"type": "filter_material", "inputs": [2], "_output": [0], "value_inputs": ["metal"]}, {"type": "filter_shape", "inputs": [3], "_output": [0], "value_inputs": ["cube"]}, {"type": "count", "inputs": [4], "_output": 1, "value_inputs": []}], "answer": 1, "template_filename": "1obj.json", "question_family_index": 0, "question_index": 95}, {"split": "train_full", "image_filename": "CLEVR_train_full_000120.png", "image_index": 120, "image": "CLEVR_train_full_000120", "question": "small yellow matte cylinder", "program": [{"type": "scene", "inputs": [], "_output": [0], "value_inputs": []}, {"type": "filter_size", "inputs": [0], "_output": [], "value_inputs": ["small"]}, {"type": "filter_color", "inputs": [1], "_output": [], "value_inputs": ["yellow"]}, {"type": "filter_material", "inputs": [2], "_output": [], "value_inputs": ["rubber"]}, {"type": "filter_shape", "inputs": [3], "_output": [], "value_inputs": ["cylinder"]}, {"type": "count", "inputs": [4], "_output": 0, "value_inputs": []}], "answer": 0, "template_filename": "1obj.json", "question_family_index": 0, "question_index": 96}, {"split": "train_full", "image_filename": "CLEVR_train_full_000121.png", "image_index": 121, "image": "CLEVR_train_full_000121", "question": "tiny purple matte ball", "program": [{"type": "scene", "inputs": [], "_output": [0], "value_inputs": []}, {"type": "filter_size", "inputs": [0], "_output": [0], "value_inputs": ["small"]}, {"type": "filter_color", "inputs": [1], "_output": [0], "value_inputs": ["purple"]}, {"type": "filter_material", "inputs": [2], "_output": [0], "value_inputs": ["rubber"]}, {"type": "filter_shape", "inputs": [3], "_output": [0], "value_inputs": ["sphere"]}, {"type": "count", "inputs": [4], "_output": 1, "value_inputs": []}], "answer": 1, "template_filename": "1obj.json", "question_family_index": 0, "question_index": 97}, {"split": "train_full", "image_filename": "CLEVR_train_full_000121.png", "image_index": 121, "image": "CLEVR_train_full_000121", "question": "big purple matte cylinder", "program": [{"type": "scene", "inputs": [], "_output": [0], "value_inputs": []}, {"type": "filter_size", "inputs": [0], "_output": [], "value_inputs": ["large"]}, {"type": "filter_color", "inputs": [1], "_output": [], "value_inputs": ["purple"]}, {"type": "filter_material", "inputs": [2], "_output": [], "value_inputs": ["rubber"]}, {"type": "filter_shape", "inputs": [3], "_output": [], "value_inputs": ["cylinder"]}, {"type": "count", "inputs": [4], "_output": 0, "value_inputs": []}], "answer": 0, "template_filename": "1obj.json", "question_family_index": 0, "question_index": 98}, {"split": "train_full", "image_filename": "CLEVR_train_full_000122.png", "image_index": 122, "image": "CLEVR_train_full_000122", "question": "tiny yellow matte ball", "program": [{"type": "scene", "inputs": [], "_output": [0], "value_inputs": []}, {"type": "filter_size", "inputs": [0], "_output": [0], "value_inputs": ["small"]}, {"type": "filter_color", "inputs": [1], "_output": [0], "value_inputs": ["yellow"]}, {"type": "filter_material", "inputs": [2], "_output": [0], "value_inputs": ["rubber"]}, {"type": "filter_shape", "inputs": [3], "_output": [0], "value_inputs": ["sphere"]}, {"type": "count", "inputs": [4], "_output": 1, "value_inputs": []}], "answer": 1, "template_filename": "1obj.json", "question_family_index": 0, "question_index": 99}, {"split": "train_full", "image_filename": "CLEVR_train_full_000122.png", "image_index": 122, "image": "CLEVR_train_full_000122", "question": "large brown rubber cube", "program": [{"type": "scene", "inputs": [], "_output": [0], "value_inputs": []}, {"type": "filter_size", "inputs": [0], "_output": [], "value_inputs": ["large"]}, {"type": "filter_color", "inputs": [1], "_output": [], "value_inputs": ["brown"]}, {"type": "filter_material", "inputs": [2], "_output": [], "value_inputs": ["rubber"]}, {"type": "filter_shape", "inputs": [3], "_output": [], "value_inputs": ["cube"]}, {"type": "count", "inputs": [4], "_output": 0, "value_inputs": []}], "answer": 0, "template_filename": "1obj.json", "question_family_index": 0, "question_index": 100}]}